build/lib/energybot/bot.py
build/lib/energybot/config.py
build/lib/energybot/db/init_queue.py
build/lib/energybot/db/models.py
build/lib/energybot/db/sqlite.py
build/lib/energybot/handlers/process.py
build/lib/energybot/helpers/data.py
build/lib/energybot/helpers/messages.py
build/lib/energybot/tasks/sync.py
build/lib/energybot/tasks/worker.py
build/lib/providers/energy_ua.py
build/lib/providers/poe.py
energybot/bot.py
energybot/config.py
energybot/db/init_queue.py
energybot/db/models.py
energybot/db/sqlite.py
energybot/handlers/process.py
energybot/helpers/data.py
energybot/helpers/messages.py
energybot/tasks/sync.py
energybot/tasks/worker.py
providers/energy_ua.py
providers/poe.py
energybot-1.1.dist-info/METADATA
energybot-1.1.dist-info/WHEEL
energybot-1.1.dist-info/entry_points.txt
energybot-1.1.dist-info/top_level.txt
energybot-1.1.dist-info/RECORD
