Metadata-Version: 2.1
Name: energybot
Version: 1.1
Summary: You personal assistant
Home-page: https://github.com/hrebynakha/e-energy.git
Author: A. Hrebynakha
Author-email: hrebynakha@gmail.com
License: MIT
Requires-Dist: markdown
Requires-Dist: beautifulsoup4
Requires-Dist: pyTelegramBotAPI
